{
    "resolved": 239,
    "open": 1681,
    "due": 9,
    "unresolvable": 51,
    "brier": 0.257,
    "hit_rate": 0.56,
    "per_horizon": {
        "24h": {
            "resolved": 239,
            "brier": 0.257,
            "hit_rate": 0.56
        }
    },
    "calibration": [
        {
            "bin": "0\u201320%",
            "n": 33,
            "avg_predicted": 0.12,
            "observed": 0.09
        },
        {
            "bin": "20\u201340%",
            "n": 53,
            "avg_predicted": 0.29,
            "observed": 0.08
        },
        {
            "bin": "40\u201360%",
            "n": 76,
            "avg_predicted": 0.49,
            "observed": 0.09
        },
        {
            "bin": "60\u201380%",
            "n": 56,
            "avg_predicted": 0.67,
            "observed": 0.14
        },
        {
            "bin": "80\u2013100%",
            "n": 21,
            "avg_predicted": 0.83,
            "observed": 0.19
        }
    ],
    "personas": {
        "Strategist": {
            "resolved": 239,
            "brier": 0.302
        },
        "Economist": {
            "resolved": 239,
            "brier": 0.317
        },
        "Naturalist": {
            "resolved": 239,
            "brier": 0.352
        },
        "Skeptic": {
            "resolved": 238,
            "brier": 0.191
        }
    },
    "models": {
        "llama3.1": {
            "resolved": 955,
            "brier": 0.291
        }
    },
    "recent": [
        {
            "statement": "NG=F drops by 2% within the next 24h",
            "horizon": "24h",
            "probability": 0.55,
            "location": "None",
            "outcome": 0.0,
            "verdict": "no",
            "evidence": "No captured signal concerns this forecast, and a 2% move in NG=F would certainly have been captured within the closed window.",
            "resolved_ms": 1784700643163,
            "ts": 1784614164673
        },
        {
            "statement": "NG=F will drop by 2% over the next 24h",
            "horizon": "24h",
            "probability": 0.43,
            "location": "None",
            "outcome": 0.0,
            "verdict": "no",
            "evidence": "No signal captured any price data for NG=F, so the claimed 2% drop cannot be confirmed within the closed window.",
            "resolved_ms": 1784700640934,
            "ts": 1784612331718
        },
        {
            "statement": "US natural gas prices will surge due to a supply disruption in the Gulf Coast region.",
            "horizon": "24h",
            "probability": 0.1,
            "location": "Gulf Coast region",
            "outcome": 0.0,
            "verdict": "no",
            "evidence": "No signal references US natural gas prices or any Gulf Coast supply disruption; only crude oil (Brent/WTI) prices appear, none showing a natural gas surge.",
            "resolved_ms": 1784697019225,
            "ts": 1784608651750
        },
        {
            "statement": "Oil prices will surge due to a disruption in Strait of Hormuz shipping.",
            "horizon": "24h",
            "probability": 0.19,
            "location": "Strait of Hormuz",
            "outcome": 0.0,
            "verdict": "no",
            "evidence": "WTI rose only 0.44% and Brent 1.36%, showing no price surge despite Hormuz transits being 30% below average, so the forecast event did not occur.",
            "resolved_ms": 1784697016057,
            "ts": 1784608651750
        },
        {
            "statement": "NG=F will drop by more than 1% in the next 24h",
            "horizon": "24h",
            "probability": 0.49,
            "location": "None",
            "outcome": 0.0,
            "verdict": "no",
            "evidence": "No captured signal concerns this forecast, so there is no evidence the event occurred within its closed window.",
            "resolved_ms": 1784693404102,
            "ts": 1784606813153
        },
        {
            "statement": "NG=F will drop by 2% within the next 24 hours",
            "horizon": "24h",
            "probability": 0.34,
            "location": "None",
            "outcome": 0.0,
            "verdict": "no",
            "evidence": "No captured signal concerns this forecast, and a 2% NG=F price drop within the window would have been recorded if it occurred.",
            "resolved_ms": 1784693401824,
            "ts": 1784604958054
        },
        {
            "statement": "WTI Crude Oil price will drop by at least 2% within the next 24h",
            "horizon": "24h",
            "probability": 0.43,
            "location": "None",
            "outcome": 0.0,
            "verdict": "no",
            "evidence": "The latest WTI snapshot shows the price at 85.2 $/bbl up +2.37%, rising rather than dropping 2%, so the forecast did not occur.",
            "resolved_ms": 1784689794686,
            "ts": 1784603108458
        },
        {
            "statement": "The price of WTI Crude Oil will drop by at least 2% within the next 24 hours.",
            "horizon": "24h",
            "probability": 0.33,
            "location": "None",
            "outcome": 0.0,
            "verdict": "no",
            "evidence": "The current snapshot shows WTI at 85.2 $/bbl up +2.37%, not dropping, and no signal shows a 2% decline within the window.",
            "resolved_ms": 1784689789292,
            "ts": 1784601275878
        },
        {
            "statement": "WTI Crude Oil price drops by 1.5% within the next 24 hours",
            "horizon": "24h",
            "probability": 0.26,
            "location": "None",
            "outcome": 0.0,
            "verdict": "no",
            "evidence": "WTI rose throughout the window, ending at +2.8% (85.56 $/bbl) rather than dropping 1.5%.",
            "resolved_ms": 1784686180733,
            "ts": 1784599435000
        },
        {
            "statement": "The price of WTI Crude Oil will increase by at least 2% within the next 24 hours.",
            "horizon": "24h",
            "probability": 0.53,
            "location": "None",
            "outcome": 0.0,
            "verdict": "no",
            "evidence": "WTI moved from 84.65 (S1) at forecast time to 85.56 (S12) at window close, an increase of only ~1.07%, short of the required 2%.",
            "resolved_ms": 1784686177155,
            "ts": 1784597591643
        },
        {
            "statement": "Natural Gas (Henry Hub) price will drop by at least 0.5% in the next 24 hours",
            "horizon": "24h",
            "probability": 0.63,
            "location": "None",
            "outcome": 0.0,
            "verdict": "no",
            "evidence": "S14 shows Henry Hub natural gas at 2.89 $/MMBtu up +1.08%, the opposite of the forecasted 0.5% drop.",
            "resolved_ms": 1784682559607,
            "ts": 1784595748921
        },
        {
            "statement": "WTI Crude Oil price will drop by at least 1% in the next 24 hours",
            "horizon": "24h",
            "probability": 0.59,
            "location": "None",
            "outcome": 0.0,
            "verdict": "no",
            "evidence": "The latest WTI reading rose to 84.82 $/bbl (+1.91%), showing a gain rather than the required 1% drop.",
            "resolved_ms": 1784678950213,
            "ts": 1784592062368
        }
    ]
}
