{
    "resolved": 316,
    "open": 1943,
    "due": 23,
    "unresolvable": 51,
    "brier": 0.262,
    "hit_rate": 0.55,
    "per_horizon": {
        "24h": {
            "resolved": 285,
            "brier": 0.265,
            "hit_rate": 0.54
        },
        "week": {
            "resolved": 31,
            "brier": 0.228,
            "hit_rate": 0.61
        }
    },
    "calibration": [
        {
            "bin": "0\u201320%",
            "n": 35,
            "avg_predicted": 0.12,
            "observed": 0.09
        },
        {
            "bin": "20\u201340%",
            "n": 73,
            "avg_predicted": 0.29,
            "observed": 0.05
        },
        {
            "bin": "40\u201360%",
            "n": 99,
            "avg_predicted": 0.49,
            "observed": 0.09
        },
        {
            "bin": "60\u201380%",
            "n": 83,
            "avg_predicted": 0.67,
            "observed": 0.16
        },
        {
            "bin": "80\u2013100%",
            "n": 26,
            "avg_predicted": 0.82,
            "observed": 0.15
        }
    ],
    "personas": {
        "Strategist": {
            "resolved": 316,
            "brier": 0.309
        },
        "Economist": {
            "resolved": 316,
            "brier": 0.329
        },
        "Naturalist": {
            "resolved": 316,
            "brier": 0.351
        },
        "Skeptic": {
            "resolved": 315,
            "brier": 0.195
        }
    },
    "models": {
        "llama3.1": {
            "resolved": 1263,
            "brier": 0.296
        }
    },
    "recent": [
        {
            "statement": "NG=F will move up by at least 2% in the next 24 hours",
            "horizon": "24h",
            "probability": 0.33,
            "location": "None",
            "outcome": 0.0,
            "verdict": "no",
            "evidence": "No captured signal shows NG=F moved up by at least 2% within the window, and such a move would have been captured.",
            "resolved_ms": 1784811481797,
            "ts": 1784721467057
        },
        {
            "statement": "BZ=F will close 2.5% higher",
            "horizon": "24h",
            "probability": 0.34,
            "location": "None",
            "outcome": 0.0,
            "verdict": "no",
            "evidence": "No captured signal shows BZ=F closing 2.5% higher within the window, and such a move would have been recorded.",
            "resolved_ms": 1784804264484,
            "ts": 1784717788345
        },
        {
            "statement": "The Brent Crude price will drop by more than 5% in the next 24 hours.",
            "horizon": "24h",
            "probability": 0.27,
            "location": "None",
            "outcome": 0.0,
            "verdict": "no",
            "evidence": "Brent fell from 94.03 to 92.73 (-1.42%), far short of the required 5% drop.",
            "resolved_ms": 1784804260573,
            "ts": 1784715949711
        },
        {
            "statement": "NG=F will fall by at least 2% in the next 24 hours",
            "horizon": "24h",
            "probability": 0.55,
            "location": "None",
            "outcome": 0.0,
            "verdict": "no",
            "evidence": "No captured signal concerns this forecast, so a 2% drop in NG=F cannot be confirmed within the window.",
            "resolved_ms": 1784804257266,
            "ts": 1784712254215
        },
        {
            "statement": "Oil prices will rise by 2% in the next 24 hours",
            "horizon": "24h",
            "probability": 0.49,
            "location": "Strait of Hormuz",
            "outcome": 0.0,
            "verdict": "no",
            "evidence": "Brent Crude is down 8.26% rather than up 2%, showing oil prices fell during the window.",
            "resolved_ms": 1784797030482,
            "ts": 1784649150125
        },
        {
            "statement": "The price of WTI Crude Oil will rise to $90/bbl within the next 24h",
            "horizon": "24h",
            "probability": 0.25,
            "location": "None",
            "outcome": 0.0,
            "verdict": "no",
            "evidence": "WTI Crude Oil is at 89.59 $/bbl, below the $90 threshold, so the forecast target was not reached.",
            "resolved_ms": 1784793427223,
            "ts": 1784704881987
        },
        {
            "statement": "The US crude oil price will rise by at least 2% in the next 24 hours",
            "horizon": "24h",
            "probability": 0.58,
            "location": "None",
            "outcome": 1.0,
            "verdict": "yes",
            "evidence": "S12 shows WTI Crude Oil (US crude) at 89.59 $/bbl, up +3.18%, exceeding the 2% threshold.",
            "resolved_ms": 1784793420448,
            "ts": 1784703053545
        },
        {
            "statement": "The price of CL=F will increase by at least 2% in the next 24 hours",
            "horizon": "24h",
            "probability": 0.81,
            "location": "Strait of Hormuz",
            "outcome": 0.0,
            "verdict": "no",
            "evidence": "No signal shows CL=F rising 2%; the [now] crude anchor (Brent) instead fell 8.42%, indicating no such increase occurred.",
            "resolved_ms": 1784793417073,
            "ts": 1784680957526
        },
        {
            "statement": "WTI Crude Oil price will drop by at least 2% in the next 24 hours",
            "horizon": "24h",
            "probability": 0.5,
            "location": "None",
            "outcome": 0.0,
            "verdict": "no",
            "evidence": "The latest [now] WTI signal shows the price at 88 $/bbl up +1.35%, not dropping 2%, and all prior signals show gains.",
            "resolved_ms": 1784786188695,
            "ts": 1784699349538
        },
        {
            "statement": "CL=F will increase by 2% in the next 24 hours",
            "horizon": "24h",
            "probability": 0.72,
            "location": "None",
            "outcome": 0.0,
            "verdict": "no",
            "evidence": "No captured signal shows CL=F increased by 2% within the window, and a move that large would have been recorded.",
            "resolved_ms": 1784786185783,
            "ts": 1784697481414
        },
        {
            "statement": "A cyberattack will occur on a major oil company within the next week.",
            "horizon": "week",
            "probability": 0.42,
            "location": "None",
            "outcome": 0.0,
            "verdict": "no",
            "evidence": "No signal reports any cyberattack on an oil company; signals only show oil prices, FOMC schedules, and volatility indices.",
            "resolved_ms": 1784786182339,
            "ts": 1784178888027
        },
        {
            "statement": "A tropical cyclone will make landfall in the Philippines within the next week.",
            "horizon": "week",
            "probability": 0.7,
            "location": "Philippines",
            "outcome": 0.0,
            "verdict": "no",
            "evidence": "The three named tropical cyclones (BERTHA, FAUSTO, ELIDA) are located far from the Philippines with zero population affected, and no signal shows any cyclone landfall in the Philippines.",
            "resolved_ms": 1784786180199,
            "ts": 1784178888027
        }
    ],
    "self_calibration": {
        "enabled": true,
        "feedback": false,
        "method": "platt",
        "fallback": "none",
        "fitted": true,
        "resolved_n": 316,
        "base_rate": 0.1044,
        "brier_raw": 0.2617,
        "brier_base_rate": 0.0935,
        "brier_calibrated_oos": null,
        "brier_calibrated_oos_n": 0,
        "note": "Published headline probability is RAW conviction (unchanged); this is the honest companion. Calibration fixes overconfidence, not discrimination \u2014 see /calibration."
    }
}
