{
    "resolved": 200,
    "open": 1490,
    "due": 4,
    "unresolvable": 51,
    "brier": 0.265,
    "hit_rate": 0.55,
    "per_horizon": {
        "24h": {
            "resolved": 200,
            "brier": 0.265,
            "hit_rate": 0.55
        }
    },
    "calibration": [
        {
            "bin": "0\u201320%",
            "n": 30,
            "avg_predicted": 0.12,
            "observed": 0.07
        },
        {
            "bin": "20\u201340%",
            "n": 40,
            "avg_predicted": 0.28,
            "observed": 0.1
        },
        {
            "bin": "40\u201360%",
            "n": 57,
            "avg_predicted": 0.49,
            "observed": 0.11
        },
        {
            "bin": "60\u201380%",
            "n": 53,
            "avg_predicted": 0.67,
            "observed": 0.15
        },
        {
            "bin": "80\u2013100%",
            "n": 20,
            "avg_predicted": 0.83,
            "observed": 0.2
        }
    ],
    "personas": {
        "Strategist": {
            "resolved": 200,
            "brier": 0.311
        },
        "Economist": {
            "resolved": 200,
            "brier": 0.321
        },
        "Naturalist": {
            "resolved": 200,
            "brier": 0.363
        },
        "Skeptic": {
            "resolved": 199,
            "brier": 0.193
        }
    },
    "models": {
        "llama3.1": {
            "resolved": 799,
            "brier": 0.297
        }
    },
    "recent": [
        {
            "statement": "The price of Natural Gas (Henry Hub) will drop by at least 2% in the next 24 hours",
            "horizon": "24h",
            "probability": 0.75,
            "location": "None",
            "outcome": 0.0,
            "verdict": "no",
            "evidence": "The only Henry Hub natural gas signal (S14) shows a +0.52% move, not a drop of at least 2%.",
            "resolved_ms": 1784626117320,
            "ts": 1784538450342
        },
        {
            "statement": "The price of Natural Gas (Henry Hub) will increase by at least 1.5% in the next 24 hours.",
            "horizon": "24h",
            "probability": 0.71,
            "location": "None",
            "outcome": 0.0,
            "verdict": "no",
            "evidence": "The only Henry Hub signal (S14) shows +0.52%, well below the required 1.5% increase.",
            "resolved_ms": 1784626113182,
            "ts": 1784536599381
        },
        {
            "statement": "WTI Crude Oil price will drop by at least 2% in the next 24 hours",
            "horizon": "24h",
            "probability": 0.5,
            "location": "None",
            "outcome": 1.0,
            "verdict": "yes",
            "evidence": "S11 shows WTI Crude Oil at -2.13%, exceeding the 2% drop threshold within the forecast window.",
            "resolved_ms": 1784622510462,
            "ts": 1784534752075
        },
        {
            "statement": "WTI Crude Oil price will drop by 2% within the next 24h",
            "horizon": "24h",
            "probability": 0.26,
            "location": "None",
            "outcome": 1.0,
            "verdict": "yes",
            "evidence": "S11 shows WTI Crude Oil at 81.46 $/bbl with a -2.13% change, exceeding the 2% drop threshold within the window.",
            "resolved_ms": 1784622506845,
            "ts": 1784532912762
        },
        {
            "statement": "WTI Crude Oil price will rise by at least 2% within the next 24 hours",
            "horizon": "24h",
            "probability": 0.59,
            "location": "None",
            "outcome": 0.0,
            "verdict": "no",
            "evidence": "The latest WTI snapshot shows 82.49 $/bbl at -0.89%, a decline rather than the required 2% rise.",
            "resolved_ms": 1784618902298,
            "ts": 1784531075474
        },
        {
            "statement": "The price of Brent Crude will drop by more than 2% within the next 24 hours",
            "horizon": "24h",
            "probability": 0.29,
            "location": "Strait of Hormuz",
            "outcome": 0.0,
            "verdict": "no",
            "evidence": "S14 shows Brent Crude at -0.29%, far short of the required >2% drop within the window.",
            "resolved_ms": 1784618899829,
            "ts": 1784529245859
        },
        {
            "statement": "The price of Natural Gas will drop by 5% within the next 24 hours",
            "horizon": "24h",
            "probability": 0.3,
            "location": "None",
            "outcome": 0.0,
            "verdict": "no",
            "evidence": "No signal reports natural gas prices at all, so the claimed 5% drop is not shown; only crude, Brent, and equity index data are present.",
            "resolved_ms": 1784618897235,
            "ts": 1784527387550
        },
        {
            "statement": "The price of Corn will drop by 2% within the next 24 hours",
            "horizon": "24h",
            "probability": 0.36,
            "location": "None",
            "outcome": 0.0,
            "verdict": "no",
            "evidence": "No signal references corn prices at all, so the claimed 2% drop is not shown to have occurred within the window.",
            "resolved_ms": 1784615290796,
            "ts": 1784527387550
        },
        {
            "statement": "The price of WTI Crude Oil will drop by 3% within the next 24 hours",
            "horizon": "24h",
            "probability": 0.28,
            "location": "None",
            "outcome": 0.0,
            "verdict": "no",
            "evidence": "The latest WTI signal shows only -1.25% (max observed -1.35%), far short of the required 3% drop.",
            "resolved_ms": 1784615282544,
            "ts": 1784527387550
        },
        {
            "statement": "Natural Gas (Henry Hub) price will drop by at least 2% within the next 24 hours.",
            "horizon": "24h",
            "probability": 0.67,
            "location": "None",
            "outcome": 0.0,
            "verdict": "no",
            "evidence": "The only Henry Hub natural gas signal (S12) shows +0.59%, an increase rather than the required 2% drop.",
            "resolved_ms": 1784615279843,
            "ts": 1784525535987
        },
        {
            "statement": "The EIA weekly petroleum status report will move CL=F by +1.5%.",
            "horizon": "24h",
            "probability": 0.81,
            "location": "None",
            "outcome": 0.0,
            "verdict": "no",
            "evidence": "The EIA petroleum report is scheduled for 2026-07-22, after the forecast window closed on 2026-07-21, and no signal shows any CL=F move of +1.5%.",
            "resolved_ms": 1784611676947,
            "ts": 1784523705430
        },
        {
            "statement": "The price of WTI Crude Oil will drop by at least 2% within the next 24h",
            "horizon": "24h",
            "probability": 0.29,
            "location": "None",
            "outcome": 0.0,
            "verdict": "no",
            "evidence": "The latest WTI snapshot shows only -1.17% (with earlier readings of -1.41% and -1.01%), none reaching the required 2% drop.",
            "resolved_ms": 1784611674378,
            "ts": 1784521875143
        }
    ]
}
